<?xml version="1.0"?>
<FileZilla3 version="3.25.0" platform="mac">
	<Settings>
		<Setting name="Use Pasv mode">1</Setting>
		<Setting name="Limit local ports">0</Setting>
		<Setting name="Limit ports low">6000</Setting>
		<Setting name="Limit ports high">7000</Setting>
		<Setting name="Limit ports offset">0</Setting>
		<Setting name="External IP mode">0</Setting>
		<Setting name="External IP" />
		<Setting name="External address resolver">http://ip.filezilla-project.org/ip.php</Setting>
		<Setting name="Last resolved IP" />
		<Setting name="No external ip on local conn">1</Setting>
		<Setting name="Pasv reply fallback mode">0</Setting>
		<Setting name="Timeout">20</Setting>
		<Setting name="Logging Debug Level">0</Setting>
		<Setting name="Logging Raw Listing">0</Setting>
		<Setting name="fzsftp executable" />
		<Setting name="Allow transfermode fallback">1</Setting>
		<Setting name="Reconnect count">2</Setting>
		<Setting name="Reconnect delay">5</Setting>
		<Setting name="Enable speed limits">0</Setting>
		<Setting name="Speedlimit inbound">100</Setting>
		<Setting name="Speedlimit outbound">20</Setting>
		<Setting name="Speedlimit burst tolerance">0</Setting>
		<Setting name="Preallocate space">0</Setting>
		<Setting name="View hidden files">0</Setting>
		<Setting name="Preserve timestamps">0</Setting>
		<Setting name="Socket recv buffer size (v2)">4194304</Setting>
		<Setting name="Socket send buffer size (v2)">262144</Setting>
		<Setting name="FTP Keep-alive commands">0</Setting>
		<Setting name="FTP Proxy type">0</Setting>
		<Setting name="FTP Proxy host" />
		<Setting name="FTP Proxy user" />
		<Setting name="FTP Proxy password" />
		<Setting name="FTP Proxy login sequence" />
		<Setting name="SFTP keyfiles" />
		<Setting name="SFTP compression">0</Setting>
		<Setting name="Proxy type">0</Setting>
		<Setting name="Proxy host" />
		<Setting name="Proxy port">0</Setting>
		<Setting name="Proxy user" />
		<Setting name="Proxy password" />
		<Setting name="Logging file" />
		<Setting name="Logging filesize limit">10</Setting>
		<Setting name="Logging show detailed logs">0</Setting>
		<Setting name="Size format">0</Setting>
		<Setting name="Size thousands separator">1</Setting>
		<Setting name="Size decimal places">1</Setting>
		<Setting name="TCP Keepalive Interval">15</Setting>
		<Setting name="Cache TTL">600</Setting>
		<Setting name="Number of Transfers">2</Setting>
		<Setting name="Ascii Binary mode">0</Setting>
		<Setting name="Auto Ascii files">am|asp|bat|c|cfm|cgi|conf|cpp|css|dhtml|diz|h|hpp|htm|html|in|inc|java|js|jsp|lua|m4|mak|md5|nfo|nsi|pas|patch|php|phtml|pl|po|py|qmail|sh|sha1|sha256|sha512|shtml|sql|svg|tcl|tpl|txt|vbs|xhtml|xml|xrc</Setting>
		<Setting name="Auto Ascii no extension">1</Setting>
		<Setting name="Auto Ascii dotfiles">1</Setting>
		<Setting name="Language Code" />
		<Setting name="Last Server Path">1 0 14 sho-hirano.xyz 11 public_html</Setting>
		<Setting name="Concurrent download limit">0</Setting>
		<Setting name="Concurrent upload limit">0</Setting>
		<Setting name="Update Check">1</Setting>
		<Setting name="Update Check Interval">7</Setting>
		<Setting name="Last automatic update check">2017-10-02 16:16:41</Setting>
		<Setting name="Last automatic update version">3.25.0</Setting>
		<Setting name="Update Check New Version">nightly 2017-10-02 http://filezilla-project.org/nightlies/2017-10-02/x86_64-apple-darwin13.4.0/FileZilla3.app.tar.bz2 10610001 sha512 7dc151927a421d5b3a185658c6151ca0a2f90ad17756ad857e10b74d001f61aae7b2d7f464dab324a44f930ce7d71aa73120c2c65f38e16b904c6188e22155bf 
release 3.28.0 http://downloads.sourceforge.net/filezilla/FileZilla_3.28.0_macosx-x86.app.tar.bz2 10478869 sha512 a4b409bec7c90cc22df2ed1dabc3cb154a01f5d5ba1e7f745cb9eb3bab7367b23e48f5800f350b46b4bf1fccf7b5b5e333d6f86b0ab9d51e651b7ab84dc4333e

3.28.0 (2017-09-29)

+ *nix: Official Linux binaries are now built for Debian 9 (Stretch)
- Do not disable password saving settings if fzdefaults.xml contains a kiosk mode setting of 0.

3.28.0-rc1 (2017-09-22)

+ Add "Close once" as queue completion action
- Fixed crash if FileZilla is forced to close, e.g. when the system is shutting down, while there are open dialogs
- If the transfer queue asks for a password and the password dialog is canceled the queue processing is now stopped
- OS X, *nix: Improve detection of invalid character encodings in local filenames 
- Fix potential crash expanding directory tree items while changing selections

3.27.1 (2017-08-14)

! Change client identification string if connecting with SFTP due to OpenSSH disregarding the supported ciphers announced by the client, resulting in less secure algorithms being chosen by OpenSSH.
- MSW: Improve handling of NTFS reparse points
- MSW: If running the installer with /S, previous versions where not uninstalled prior to the new version being installed
- MSW: The installer can be run with /quiet for a semi-silent installation
- OS X, *nix: Potential fix for a rare crash if changing local directories while the local directory list is being updated and vice versa.

3.27.0.1 (2017-07-19)

- MSW: Add misssing file to .zip binary package
- MSW: Fix toolchain issues breaking the shell extension

3.27.0 (2017-07-19)

- SFTP components have been updated and are now based on PuTTY 0.70

3.27.0-rc1 (2017-07-11)

+ Support for the Storj decentralized cloud storage provider
- MSW: Fix display of file type of directories if the directory name contains a dot
- Fix assertion if entering an invalid protocol prefix into the host field on the quickconnect bar or in the site manager
- Improve error message if TLS certificate verification fails due to a missing stapled OCSP resonse
- Building and running FileZilla now depends on libfilezilla &gt;= 0.10.0 (https://lib.filezilla-project.org/)

3.26.2 (2017-06-12)

- Fixed crash if using master passwords and decrypting very long passwords

3.26.1 (2017-06-02)

- Fixed crash if changing password settings and the Site Manager contains subdirectories
- *nix: Fixed saving of sites having more than one site-specific bookmark

3.26.0 (2017-06-01)

- When changing or removing the master password, update protected credentials of server items in the transfer queue
- Fix display of remember checkbox when showing the password entry dialog for sites that have no username set and are using the "Ask" logon type
- Some icons were missing in the Windows .zip binary archive

3.26.0-rc1 (2017-05-25)

+ Passwords can now be stored encrypted, protected with a master password
+ Building and running FileZilla now depends on libfilezilla &gt;= 0.9.2 (https://lib.filezilla-project.org/).
+ Building and running FileZilla now depends on wxWidgets &gt;= 3.0.3

3.25.2 (2017-04-30)

- SFTP components have been updated and are now based on PuTTY 0.69
- Fixed potential stall during the final listing operation when finishing a queue which contained uploads

3.25.2-rc1 (2017-04-23)

- Fix crash if filters.xml has become corrupted
- Fix FTP proxy support
- Fix sending of FTP keep-alive commands
- MSW: Windows Vista is no longer supported
- MSW: File and directory icons now also appear on systems that have no Windows directory

3.25.1 (2017-03-20)

- OS X: Fixed a crash if connecting to old servers not supporting UTF-8
- Fixed timeout detection
</Setting>
		<Setting name="Update Check Check Beta">0</Setting>
		<Setting name="Show debug menu">0</Setting>
		<Setting name="File exists action download">0</Setting>
		<Setting name="File exists action upload">0</Setting>
		<Setting name="Allow ascii resume">0</Setting>
		<Setting name="Greeting version">3.25.0</Setting>
		<Setting name="Greeting resources" />
		<Setting name="Onetime Dialogs" />
		<Setting name="Show Tree Local">1</Setting>
		<Setting name="Show Tree Remote">1</Setting>
		<Setting name="File Pane Layout">0</Setting>
		<Setting name="File Pane Swap">0</Setting>
		<Setting name="Last local directory">/Users/yukiinoue/Desktop/yuki22.xsrv.jp/</Setting>
		<Setting name="Filelist directory sort">0</Setting>
		<Setting name="Filelist name sort">1</Setting>
		<Setting name="Queue successful autoclear">0</Setting>
		<Setting name="Queue column widths">180 60 180 80 60 150</Setting>
		<Setting name="Local filelist colwidths">120 80 100 191</Setting>
		<Setting name="Remote filelist colwidths">286 75 80 179 132 179</Setting>
		<Setting name="Window position and size">1 4 23 1201 794 </Setting>
		<Setting name="Splitter positions (v2)">163 -91 500000000 204 204 500000000</Setting>
		<Setting name="Local filelist sortorder">0 0</Setting>
		<Setting name="Remote filelist sortorder">0 0</Setting>
		<Setting name="Time Format" />
		<Setting name="Date Format" />
		<Setting name="Show message log">1</Setting>
		<Setting name="Show queue">1</Setting>
		<Setting name="Default editor" />
		<Setting name="Always use default editor">0</Setting>
		<Setting name="Inherit system associations">1</Setting>
		<Setting name="Custom file associations">. /Applications/TextEdit.app</Setting>
		<Setting name="Comparison mode">1</Setting>
		<Setting name="Comparison threshold">1</Setting>
		<Setting name="Site Manager position">1 17 34 1406 784 </Setting>
		<Setting name="Icon theme">default</Setting>
		<Setting name="Icon scale">125</Setting>
		<Setting name="Timestamp in message log">0</Setting>
		<Setting name="Sitemanager last selected">0/xserver</Setting>
		<Setting name="Local filelist shown columns">1111</Setting>
		<Setting name="Remote filelist shown columns">111111</Setting>
		<Setting name="Local filelist column order">0,1,2,3</Setting>
		<Setting name="Remote filelist column order">0,1,2,3,4,5</Setting>
		<Setting name="Filelist status bar">1</Setting>
		<Setting name="Filter toggle state">0</Setting>
		<Setting name="Show quickconnect bar">1</Setting>
		<Setting name="Messagelog position">0</Setting>
		<Setting name="Last connected site">0/xserver</Setting>
		<Setting name="File doubleclock action">0</Setting>
		<Setting name="Dir doubleclock action">0</Setting>
		<Setting name="Minimize to tray">0</Setting>
		<Setting name="Search column widths" />
		<Setting name="Search column shown" />
		<Setting name="Search column order" />
		<Setting name="Search window size" />
		<Setting name="Comparison hide identical">0</Setting>
		<Setting name="Search sort order" />
		<Setting name="Edit track local">1</Setting>
		<Setting name="Prevent idle sleep">1</Setting>
		<Setting name="Filteredit window size" />
		<Setting name="Enable invalid char filter">1</Setting>
		<Setting name="Invalid char replace">_</Setting>
		<Setting name="Already connected choice">0</Setting>
		<Setting name="Edit status dialog size" />
		<Setting name="Display current speed">0</Setting>
		<Setting name="Toolbar hidden">0</Setting>
		<Setting name="Strip VMS revisions">0</Setting>
		<Setting name="Show Site Manager on startup">0</Setting>
		<Setting name="Prompt password change">0</Setting>
		<Setting name="Persistent Choices">1</Setting>
		<Setting name="Queue completion action">1</Setting>
		<Setting name="Queue completion command" />
		<Setting name="Drag and Drop disabled">0</Setting>
		<Setting name="Disable update footer">0</Setting>
		<Setting name="Config Location">/Users/yukiinoue/.config/filezilla/</Setting>
		<Setting name="Kiosk mode">0</Setting>
		<Setting name="Disable update check">0</Setting>
		<Setting name="Cache directory" />
		<LastServer>
			<Host>yuki22.xsrv.jp</Host>
			<Port>21</Port>
			<Protocol>0</Protocol>
			<Type>0</Type>
			<User>yuki22</User>
			<Pass encoding="base64">cHcxZGJhNzU=</Pass>
			<Logontype>1</Logontype>
			<TimezoneOffset>0</TimezoneOffset>
			<PasvMode>MODE_DEFAULT</PasvMode>
			<MaximumMultipleConnections>0</MaximumMultipleConnections>
			<EncodingType>Auto</EncodingType>
			<BypassProxy>0</BypassProxy>
			<Name>xserver</Name>
		</LastServer>
	</Settings>
</FileZilla3>
